Metadata-Version: 1.0
Name: fannys-math-package
Version: 0.1.1
Summary: An awesome package that does simple math
Home-page: UNKNOWN
Author: Fanny
Author-email: UNKNOWN
License: UNKNOWN
Platform: UNKNOWN
